{"trial_id": "0001", "hyperparameters": {"space": [{"class_name": "Int", "config": {"name": "units", "default": null, "conditions": [], "min_value": 64, "max_value": 256, "step": 32, "sampling": null}}, {"class_name": "Choice", "config": {"name": "dropout", "default": 0.05, "conditions": [], "values": [0.05, 0.1, 0.15], "ordered": true}}, {"class_name": "Choice", "config": {"name": "learning_rate", "default": 0.01, "conditions": [], "values": [0.01, 0.001, 0.0001], "ordered": true}}], "values": {"units": 96, "dropout": 0.1, "learning_rate": 0.001, "tuner/epochs": 3, "tuner/initial_epoch": 0, "tuner/bracket": 2, "tuner/round": 0}}, "metrics": {"metrics": {"loss": {"direction": "min", "observations": [{"value": [1.2776685953140259], "step": 2}]}, "accuracy": {"direction": "max", "observations": [{"value": [0.5437999963760376], "step": 2}]}, "val_loss": {"direction": "min", "observations": [{"value": [1.128028154373169], "step": 2}]}, "val_accuracy": {"direction": "max", "observations": [{"value": [0.5945000052452087], "step": 2}]}}}, "score": 0.5945000052452087, "best_step": 2, "status": "COMPLETED"}